fusion360_streamer/__init__.py
fusion360_streamer/__main__.py
fusion360_streamer/application.py
fusion360_streamer/constants.py
fusion360_streamer/gui.py
fusion360_streamer/package.py
fusion360_streamer-1.0.18.dist-info/LICENSE
fusion360_streamer-1.0.18.dist-info/METADATA
fusion360_streamer-1.0.18.dist-info/WHEEL
fusion360_streamer-1.0.18.dist-info/entry_points.txt
fusion360_streamer-1.0.18.dist-info/top_level.txt
fusion360_streamer-1.0.18.dist-info/RECORD
