Metadata-Version: 2.1
Name: fusion360-streamer
Version: 1.0.18
Summary: Autodesk Fusion 360 Streamer python implementation
Home-page: https://github.com/dzervas/fusion360-streamer
Author: Dimitris Zervas
Author-email: dzervas@dzervas.gr
License: GPLv3
Platform: UNKNOWN
License-File: LICENSE
Requires-Dist: certifi (==2023.5.7)
Requires-Dist: charset-normalizer (==3.1.0)
Requires-Dist: humanize (==4.7.0)
Requires-Dist: idna (==3.4)
Requires-Dist: prettyformatter (==2.0.13)
Requires-Dist: pyqt5-qt5 (==5.15.2)
Requires-Dist: pyqt5-sip (==12.12.1)
Requires-Dist: pyqt5 (==5.15.9)
Requires-Dist: requests (==2.31.0)
Requires-Dist: urllib3 (==2.0.3)
